cutters_common/__init__.py
cutters_common/kafka_helpers.py
cutters_common-0.1.1.dist-info/WHEEL
cutters_common-0.1.1.dist-info/METADATA
cutters_common-0.1.1.dist-info/RECORD
