Metadata-Version: 2.1
Name: cutters-common
Version: 0.1.1
Summary: 
Author: Panu Oksiala
Author-email: panu@oksiala.fi
Requires-Python: >=3.8,<4.0
Classifier: Programming Language :: Python :: 3
Classifier: Programming Language :: Python :: 3.8
Classifier: Programming Language :: Python :: 3.9
Requires-Dist: kafka-python (>=2.0.2,<3.0.0)
